pysteam/__init__.py
pysteam/autograd/__init__.py
pysteam/autograd/builtins.py
pysteam/autograd/core.py
pysteam/autograd/differential_operators.py
pysteam/autograd/extend.py
pysteam/autograd/tracer.py
pysteam/autograd/util.py
pysteam/autograd/wrap_util.py
pysteam/autograd_array/__init__.py
pysteam/autograd_array/boxes.py
pysteam/autograd_array/vjps.py
pysteam/autograd_array/vspaces.py
pysteam/autograd_se3/__init__.py
pysteam/autograd_se3/boxes.py
pysteam/autograd_se3/vjps.py
pysteam/autograd_se3/vspaces.py
pysteam/evaluable/__init__.py
pysteam/evaluable/evaluable.py
pysteam/evaluable/state_key.py
pysteam/evaluable/state_var.py
pysteam/evaluable/p2p/__init__.py
pysteam/evaluable/p2p/p2p_error_evaluator.py
pysteam/evaluable/p2p/radial_vel_error_evaluator.py
pysteam/evaluable/se3/__init__.py
pysteam/evaluable/se3/se3_evaluators.py
pysteam/evaluable/se3/se3_state_var.py
pysteam/evaluable/stereo/__init__.py
pysteam/evaluable/stereo/compose_landmark_evaluator.py
pysteam/evaluable/stereo/homo_point_error_evaluator.py
pysteam/evaluable/stereo/homo_point_state_var.py
pysteam/evaluable/stereo/stereo_error_evaluator.py
pysteam/evaluable/vspace/__init__.py
pysteam/evaluable/vspace/vspace_evaluators.py
pysteam/evaluable/vspace/vspace_state_var.py
pysteam/problem/__init__.py
pysteam/problem/cost_term.py
pysteam/problem/loss_func.py
pysteam/problem/noise_model.py
pysteam/problem/problem.py
pysteam/problem/sliding_window_filter.py
pysteam/problem/state_vector.py
pysteam/solver/__init__.py
pysteam/solver/covariance.py
pysteam/solver/dogleg_gauss_newton_solver.py
pysteam/solver/gauss_newton_solver.py
pysteam/solver/lev_marq_gauss_newton_solver.py
pysteam/solver/line_search_gauss_newton_solver.py
pysteam/solver/solver.py
pysteam/trajectory/__init__.py
pysteam/trajectory/interface.py
pysteam/trajectory/time.py
pysteam/trajectory/bspline/__init__.py
pysteam/trajectory/bspline/interface.py
pysteam/trajectory/bspline/variable.py
pysteam/trajectory/bspline/velocity_interpolator.py
asrl_pysteam-1.1.0.dist-info/LICENSE
asrl_pysteam-1.1.0.dist-info/METADATA
asrl_pysteam-1.1.0.dist-info/WHEEL
asrl_pysteam-1.1.0.dist-info/top_level.txt
asrl_pysteam-1.1.0.dist-info/RECORD
