Metadata-Version: 2.1
Name: asrl-pysteam
Version: 1.1.0
Summary: Python implementation of steam
Home-page: https://github.com/utiasASRL/pysteam
Author: Yuchen Wu
Author-email: cheney.wu@mail.utoronto.ca
License: BSD
Platform: UNKNOWN
Requires-Python: >=3.8
Requires-Dist: numpy (>=1.21.0)
Requires-Dist: scipy (>=1.7.0)
Requires-Dist: matplotlib (>=3.4.2)
Requires-Dist: asrl-pylgmath (>=1.0.2)
